nvidia/srl/_base/__init__.py
nvidia/srl/_base/py.typed
nvidia/srl/abc/__init__.py
nvidia/srl/abc/distinctive.py
nvidia/srl/abc/pose_predictor.py
nvidia/srl/abc/py.typed
nvidia/srl/abc/scene_generator.py
nvidia/srl/abc/solution_optimizer.py
nvidia/srl/abc/srl.py
nvidia/srl/abc/task.py
nvidia/srl/abc/task_generator.py
nvidia/srl/abc/task_solver.py
nvidia/srl/basics/__init__.py
nvidia/srl/basics/enum.py
nvidia/srl/basics/py.typed
nvidia/srl/basics/types.py
nvidia/srl/dev/__init__.py
nvidia/srl/dev/project_helper.py
nvidia/srl/dev/py.typed
nvidia/srl/dev/test_helper.py
nvidia/srl/tools/__init__.py
nvidia/srl/tools/compare.py
nvidia/srl/tools/hash.py
nvidia/srl/tools/list.py
nvidia/srl/tools/logger.py
nvidia/srl/tools/misc.py
nvidia/srl/tools/parameterize.py
nvidia/srl/tools/py.typed
nvidia/srl/tools/python_helper.py
nvidia/srl/tools/threading.py
nvidia/srl/types/__init__.py
nvidia/srl/types/base.py
nvidia/srl/types/image.py
nvidia/srl/types/py.typed
nvidia_srl_base-1.6.0.dist-info/licenses/LICENSE
nvidia_srl_base-1.6.0.dist-info/METADATA
nvidia_srl_base-1.6.0.dist-info/WHEEL
nvidia_srl_base-1.6.0.dist-info/top_level.txt
nvidia_srl_base-1.6.0.dist-info/RECORD
