Metadata-Version: 2.4
Name: nvidia-srl-base
Version: 1.6.0
Summary: SRL Python base package. Contains base classes, basic types, general tools, and developer utilities.
Author: NVIDIA Seattle Robotics Lab
License-Expression: Apache-2.0
Project-URL: Homepage, https://gitlab-master.nvidia.com/srl/py/base/-/blob/main/README.md
Project-URL: Documentation, https://srl.gitlab-master-pages.nvidia.com/py/base
Project-URL: Repository, https://gitlab-master.nvidia.com/srl/py/base
Project-URL: Issues, https://gitlab-master.nvidia.com/srl/py/base/-/issues
Project-URL: Changelog, https://gitlab-master.nvidia.com/srl/py/base/-/blob/main/CHANGELOG.md
Keywords: docker
Platform: any
Classifier: Operating System :: OS Independent
Classifier: Intended Audience :: Developers
Classifier: Natural Language :: English
Classifier: Programming Language :: Python :: 3
Classifier: Framework :: Robot Framework :: Library
Requires-Python: >=3.7
License-File: LICENSE
Requires-Dist: docstring-parser==0.16
Requires-Dist: importlib-metadata; python_version < "3.10"
Requires-Dist: numpy>=1.21.5
Requires-Dist: pydantic<3.0.0,>=2.7.0
Requires-Dist: pyyaml<7.0.0,>=6.0.0
Requires-Dist: setuptools-scm<9.0.0,>=8.0.0; python_version >= "3.8"
Requires-Dist: setuptools-scm<8.0,>=6.0; python_version == "3.7"
Provides-Extra: ci
Requires-Dist: numpy<3.0.0,>=2.2.5; extra == "ci"
Requires-Dist: types-pyyaml==6.0.12.20250516; extra == "ci"
Requires-Dist: usd-core==23.8; extra == "ci"
Requires-Dist: black==25.1.0; extra == "ci"
Requires-Dist: flake8==7.2.0; extra == "ci"
Requires-Dist: flake8-copyright==0.2.4; extra == "ci"
Requires-Dist: flake8-docstrings==1.7.0; extra == "ci"
Requires-Dist: flake8-isort==6.1.2; extra == "ci"
Requires-Dist: flake8-rst-docstrings==0.3.1; extra == "ci"
Requires-Dist: flake8-pyproject==1.2.3; extra == "ci"
Requires-Dist: isort==5.12.0; extra == "ci"
Requires-Dist: mypy==1.16.0; extra == "ci"
Requires-Dist: pep8-naming==0.15.1; extra == "ci"
Requires-Dist: pytest==8.4.0; extra == "ci"
Requires-Dist: pytest-cov==6.2.1; extra == "ci"
Requires-Dist: pytest-xdist==3.7.0; extra == "ci"
Requires-Dist: docutils==0.21.2; extra == "ci"
Requires-Dist: graphviz==0.20.3; extra == "ci"
Requires-Dist: sphinx==8.1.3; extra == "ci"
Requires-Dist: sphinx-rtd-theme==3.0.2; extra == "ci"
Requires-Dist: sphinx-copybutton==0.5.2; extra == "ci"
Requires-Dist: build==1.2.2.post1; extra == "ci"
Requires-Dist: twine==6.1.0; extra == "ci"
Requires-Dist: anybadge==1.16.0; extra == "ci"
Requires-Dist: black[jupyter]==25.1.0; extra == "ci"
Requires-Dist: ipykernel==6.29.5; extra == "ci"
Requires-Dist: nbclient==0.10.2; extra == "ci"
Requires-Dist: nbconvert==7.16.6; extra == "ci"
Requires-Dist: nbformat==5.10.4; extra == "ci"
Requires-Dist: nvidia-srl-jupyter-clear-output==0.7.0; extra == "ci"
Provides-Extra: dev
Requires-Dist: ipdb; extra == "dev"
Requires-Dist: ipython; extra == "dev"
Requires-Dist: nvidia-srl-dock; extra == "dev"
Requires-Dist: ipykernel; extra == "dev"
Requires-Dist: jupyter; extra == "dev"
Dynamic: license-file
